LICENSE
pytest_cache_assert/__init__.py
pytest_cache_assert/_check_assert/__init__.py
pytest_cache_assert/_check_assert/assert_config.py
pytest_cache_assert/_check_assert/assert_rules.py
pytest_cache_assert/_check_assert/cache_store.py
pytest_cache_assert/_check_assert/caching.py
pytest_cache_assert/_check_assert/config.py
pytest_cache_assert/_check_assert/constants.py
pytest_cache_assert/_check_assert/converter.py
pytest_cache_assert/_check_assert/differ.py
pytest_cache_assert/_check_assert/error_message.py
pytest_cache_assert/_check_assert/serializer.py
pytest_cache_assert/_check_assert/validator.py
pytest_cache_assert/main.py
pytest_cache_assert/plugin.py
pytest_cache_assert-4.0.0.dist-info/LICENSE
pytest_cache_assert-4.0.0.dist-info/METADATA
pytest_cache_assert-4.0.0.dist-info/WHEEL
pytest_cache_assert-4.0.0.dist-info/entry_points.txt
pytest_cache_assert-4.0.0.dist-info/RECORD
