Metadata-Version: 2.1
Name: pytest-cache-assert
Version: 4.0.0
Summary: Cache assertion data to simplify regression testing of complex serializable data
Home-page: https://github.com/kyleking/pytest_cache_assert
License: MIT
Author: Kyle King
Author-email: dev.act.kyle@gmail.com
Requires-Python: >=3.8.12,<4.0.0
Classifier: Development Status :: 5 - Production/Stable
Classifier: Framework :: Pytest
Classifier: Intended Audience :: Developers
Classifier: License :: OSI Approved :: MIT License
Classifier: Operating System :: OS Independent
Classifier: Programming Language :: Python :: 3
Classifier: Programming Language :: Python :: 3.9
Classifier: Programming Language :: Python :: 3.10
Classifier: Programming Language :: Python :: 3.11
Classifier: Programming Language :: Python :: 3.8
Classifier: Topic :: Software Development :: Testing
Requires-Dist: arrow (>=1.2.3)
Requires-Dist: corallium (>=0.3.3)
Requires-Dist: deepdiff6 (>=6.2.0)
Requires-Dist: pytest (>=6.0.0)
Project-URL: Bug Tracker, https://github.com/kyleking/pytest_cache_assert/issues
Project-URL: Changelog, https://github.com/kyleking/pytest_cache_assert/blob/main/docs/docs/CHANGELOG.md
Project-URL: Documentation, https://pytest_cache_assert.kyleking.me
Project-URL: Repository, https://github.com/kyleking/pytest_cache_assert
